Workbook

Sheet Accueil
A1: SUIVI DES MERGE CODES QVIDIAN
A2: Pilotage fonds par fonds des textes d’expérience — campagne 2026 / anticipation 2027
A4: MODE D’EMPLOI
A5: Commencez par l’onglet Suivi Qvidian. Renseignez les ID de textes et les merge codes, puis passez le statut à Terminé. Les collaborateurs à 0 an sont identifiés automatiquement pour préparer leur activation l’année suivante.
A7: Onglet | B7: Utilité
A8: Suivi Qvidian | B8: Page de travail principale : avancement par fonds, ID Qvidian et anticipation 2027.
A9: Data | B9: Référentiel des collaborateurs, expériences et merge codes.
A10: Exp individuelle + team - TCD | B10: Tableaux croisés d’expérience individuelle et par équipe.
A11: Exp moyenne par équipe gestion | B11: Synthèse des expériences moyennes par équipe.
A12: Notice | B12: Instructions historiques de mise à jour du référentiel et des TCD.

Sheet Notice
B2: Comment mettre à jour le tableau en cas d'un départ ou d'une arrivée de collaborateur ? Ou début nouvelle année
C4: Etape 1 - Informations
B5: Ajouter (arrivée) ou enlever (départ) une ligne dans l'onglet "Data"
B6: Remplir les infos (équipe, années d'expérience…)
C8: Etape 2 - Onglet TCD
B9: Cliquez n'importe où sur le premier TCD
B10: Rendez-vous dans "PivotTable Analyze"
B11: Puis sélectionnez Refresh.
B22: Répétez l'opération pour chaque TCD.

Sheet Exp individuelle + team - TCD
A1: Années d'expérience
A3: Equipe | B3: Investissement Durable
A4: Fonction | B4: (Plusieurs éléments)
A6: Étiquettes de lignes | B6: Sum of Date d'entrée dans l'industrie | C6: Sum of Nombre d'années d'expérience | D6: Sum of Date d'entrée dans la société | E6: Sum of Nombre d'années dans la société
A7: Alice Lagny | B7: 2016 | C7: 8 | D7: 2019 | E7: 5
A8: Andrea Sekularac | B8: 2016 | C8: 8 | D8: 2016 | E8: 8
A9: Edward Luu | B9: 2014 | C9: 10 | D9: 2021 | E9: 3
A10: Ludivine de Quincerot | B10: 1998 | C10: 26 | D10: 2004 | E10: 20
A11: Thomas Vincent | B11: 2005 | C11: 19 | D11: 2005 | E11: 19
A12: Total général | B12: 10049 | C12: 71 | D12: 10065 | E12: 55
A23: Expérience moyenne par équipe
A25: Equipe | B25: (Tous)
A26: Fonction | B26: (Tous)
A28: Étiquettes de lignes | B28: Average of Nombre d'années d'expérience | C28: Average of Nombre d'années dans la société
A29: Abel Amine | B29: 2 | C29: 1
A30: Alain Massiera | B30: 45 | C30: 13
A31: Alban Seydoux | B31: 24 | C31: 12
A32: Alice Lagny | B32: 8 | C32: 5
A33: Ambre Laurenson | B33: 3 | C33: 3
A34: Andrea Sekularac | B34: 8 | C34: 8
A35: Anthony Bailly | B35: 23 | C35: 17
A36: Antoine Da Silva | B36: 0 | C36: 0
A37: Céline Maréchal | B37: 26 | C37: 11
A38: Charles-Edouard Bilbault | B38: 12 | C38: 11
A39: Didier Bouvignies | B39: 38 | C39: 20
A40: Edward Luu | B40: 10 | C40: 3
... A98: Yoann Ignatiew | B98: 34 | C98: 16
A99: (vide)
A100: Gabriel Ernault | B100: 7 | C100: 7
A101: Salma Alami-Drideb | B101: 13 | C101: 13
A102: Alexandre Case | B102: 1 | C102: 1
A103: Alexandre Teran | B103: 4 | C103: 2
A104: Total général | B104: 18.540541 | C104: 10.932432

Sheet Data
A1: Nom | B1: Merge code (Exp Industrie) | C1: Merge code (Exp Société) | D1: Equipe | E1: Fonction | F1: Fonction détaillee | G1: Titre | H1: Date d'entrée dans l'industrie | I1: Nombre d'années d'expérience | J1: Date d'entrée dans la société | K1: Nombre d'années dans la société
A2: Abel Amine | B2: XPINDUS_AbelAm | C2: XPSDG_AbelAm | D2: Valor (gamme) | E2: Analyste | F2: Analyste | G2: Analyste – actions internationales | H2: 2022 | I2: =YEAR(TODAY())-H2 -> 4 | J2: 2023 | K2: =YEAR(TODAY())-J2 -> 3
A3: Alain Massiera | B3: XPSDG_ | C3: XPSDG_ | D3: Banque Privée | E3: Responsable | G3: Associé-Gérant, Responsable de la Banque privée et de la Gestion d'actifs en France | H3: 1979 | I3: =YEAR(TODAY())-H3 -> 47 | J3: 2011 | K3: =YEAR(TODAY())-J3 -> 15
A4: Alban Seydoux | B4: XPINDUS_ASeydoux | C4: XPSDG_Aseydoux | D4: Actions Thématiques | E4: Gérant | G4: Gérant analyste Petites et moyennes capitalisations Product Specialist | H4: 2000 | I4: =YEAR(TODAY())-H4 -> 26 | J4: 2012 | K4: =YEAR(TODAY())-J4 -> 14
A5: Alexandre Case | B5: XPINDUS_ACase | C5: XPSDG_ACase | D5: Risques | E5: Analyste Risques | G5: Analyste Risques | H5: 2023 | I5: =YEAR(TODAY())-H5 -> 3 | J5: 2023 | K5: =YEAR(TODAY())-J5 -> 3
A6: Alexandre Morabito | B6: XPINDUS_Morabito | C6: XPSDG_Morabito | D6: Actions Européennes | E6: Analyste | F6: Analyste/ Assistant de gestion | G6: Analyste / Assistant de gestion | H6: 2024 | I6: =YEAR(TODAY())-H6 -> 2 | J6: 2025 | K6: =YEAR(TODAY())-J6 -> 1
A7: Alexandre Teran | B7: XPINDUS_Teran | C7: XPSDG_Teran | D7: Risques | E7: Analyste Risques | G7: Analyste Risques | H7: 2020 | I7: =YEAR(TODAY())-H7 -> 6 | J7: 2022 | K7: =YEAR(TODAY())-J7 -> 4
A8: Alice Lagny | B8: XPINDUS_Lagny | C8: XPSDG_Lagny | D8: Investissement Durable | E8: Analyste | F8: Analyste | G8: Spécialiste ESG | H8: 2016 | I8: =YEAR(TODAY())-H8 -> 10 | J8: 2019 | K8: =YEAR(TODAY())-J8 -> 7
A9: Andrea Sekularac | B9: XPINDUS_AS | C9: XPSDG_AS | D9: Investissement Durable | E9: Analyste | F9: Analyste | G9: Spécialiste ESG | H9: 2016 | I9: =YEAR(TODAY())-H9 -> 10 | J9: 2016 | K9: =YEAR(TODAY())-J9 -> 10
A10: Anthony Bailly | B10: XPINDUS_Bailly | C10: XPSDG_Bailly | D10: Actions Européennes | E10: Gérant | G10: Gérant - Responsable de la gestion Actions européennes | H10: 2001 | I10: =YEAR(TODAY())-H10 -> 25 | J10: 2007 | K10: =YEAR(TODAY())-J10 -> 19
A11: Antoine Da Silva | B11: XPINDUS_ADS | C11: XPSDG_ADS | D11: Obligataire | E11: Analyste | F11: Assistant de gestion | G11: Equipe Gestion Obligataire | H11: 2024 | I11: =YEAR(TODAY())-H11 -> 2 | J11: 2024 | K11: =YEAR(TODAY())-J11 -> 2
A12: Augustin Giros | B12: XPINDUS_AGiros | C12: XPSDG_AGiros | D12: Obligataire | E12: Analyste | F12: Analyste | G12: Analyste crédit | I12: =YEAR(TODAY())-H12 -> 2026 | J12: 2026 | K12: =YEAR(TODAY())-J12 -> 0
A13: Céline Maréchal | B13: XPINDUS_CelMar | C13: XPSDG_CelMar | D13: Responsable opérationnel | E13: Responsable opérationnel | G13: Directrice Juridique et RCCI R&Co AM | H13: 1998 | I13: =YEAR(TODAY())-H13 -> 28 | J13: 2013 | K13: =YEAR(TODAY())-J13 -> 13
A14: Charles-Edouard Bilbault | B14: XPINDUS_CEB | C14: XPSDG_CEB | D14: Valor (gamme) | E14: Gérant | G14: Gérant de portefeuilles diversifiés et actions internationales | H14: 2012 | I14: =YEAR(TODAY())-H14 -> 14 | J14: 2013 | K14: =YEAR(TODAY())-J14 -> 13
A15: Didier Bouvignies | B15: XPINDUS_DB | C15: XPSDG_DB | D15: Comité exécutif | E15: Comité exécutif | G15: Associé-Gérant, Directeur des gestions | H15: 1986 | I15: =YEAR(TODAY())-H15 -> 40 | J15: 2004 | K15: =YEAR(TODAY())-J15 -> 22
A16: Edward Luu | B16: XPINDUS_Luu | C16: XPSDG_Luu | D16: Investissement Durable | E16: Analyste | F16: Analyste | G16: Analyste ESG et responsable de l'engagement | H16: 2014 | I16: =YEAR(TODAY())-H16 -> 12 | J16: 2021 | K16: =YEAR(TODAY())-J16 -> 5
A17: Clara Davitian | B17: XPINDUS_ | C17: XPSDG_ | D17: Private Asset | E17: Analyste | F17: Analyste | G17: Analyste Private Asset | H17: 2024 | I17: =YEAR(TODAY())-H17 -> 2 | J17: 2024 | K17: =YEAR(TODAY())-J17 -> 2
A18: Elsa Fernandez | B18: XPINDUS_ElsaFer | C18: XPSDG_ElsaFer | D18: Valor (gamme) | E18: Analyste | F18: Product Specialist | G18: Product Specialist - Valor | H18: 2010 | I18: =YEAR(TODAY())-H18 -> 16 | J18: 2020 | K18: =YEAR(TODAY())-J18 -> 6
A19: Emmanuel Petit | B19: XPINDUS_EP | C19: XPSDG_EP | D19: Obligataire | E19: Comité exécutif | F19: Gérant | G19: Associé-Gérant, Responsable de la gestion obligataire. Spécialisation : Credit IG et crossover | H19: 1998 | I19: =YEAR(TODAY())-H19 -> 28 | J19: 2006 | K19: =YEAR(TODAY())-J19 -> 20
A20: Éric Lancien | B20: XPINDUS_ELancien | C20: XPSDG_ELancien | D20: Responsable opérationnel | E20: Responsable opérationnel | G20: Directeur des risques, Rothschild Martin Maurel | H20: 1996 | I20: =YEAR(TODAY())-H20 -> 30 | J20: 2013 | K20: =YEAR(TODAY())-J20 -> 13
A21: Etienne Rouzeau | B21: XPINDUS_ERouzeau | C21: XPSDG_ERouzeau | D21: Solutions d'investissement | E21: Gérant | G21: Responsable des Solutions d'Investissement | H21: 1995 | I21: =YEAR(TODAY())-H21 -> 31 | J21: 2014 | K21: =YEAR(TODAY())-J21 -> 12
A22: Eva Olejniczak | B22: XPINDUS_EvaOle | C22: XPSDG_EvaOle | D22: Actions Européennes | E22: Analyste | F22: Analyste | G22: Analyste Actions Européennes | H22: 2024 | I22: =YEAR(TODAY())-H22 -> 2 | J22: 2024 | K22: =YEAR(TODAY())-J22 -> 2
A23: Fanny Daeschner | B23: XPINDUS_FanDae | C23: XPSDG_FanDae | D23: Risques | E23: Responsable opérationnel | G23: Directrice des risques, R&Co AM | H23: 2002 | I23: =YEAR(TODAY())-H23 -> 24 | J23: 2014 | K23: =YEAR(TODAY())-J23 -> 12
A24: Frédéric Chaix-Bryan | B24: XPINDUS_FredCB | C24: XPSDG_FredCB | D24: Négociation | E24: Négociateur | G24: Négociateur | H24: 1995 | I24: =YEAR(TODAY())-H24 -> 31 | J24: 2017 | K24: =YEAR(TODAY())-J24 -> 9
A25: Gabriel Ernault | B25: XPINDUS_GabErn | C25: XPSDG_GabErn | D25: Risques | E25: Responsable Risques de Marchés | G25: Responsable Risques de Marchés | H25: 2017 | I25: =YEAR(TODAY())-H25 -> 9 | J25: 2017 | K25: =YEAR(TODAY())-J25 -> 9
A26: Gabriel Hors | B26: XPINDUS_GabHors | C26: XPSDG_GabHors | D26: Actions Européennes | E26: Analyste | F26: Analyste | G26: Analyste Actions Européennes | H26: 1993 | I26: =YEAR(TODAY())-H26 -> 33 | J26: 2010 | K26: =YEAR(TODAY())-J26 -> 16
A27: Grégoire du Mesnil du Buisson | B27: XPINDUS_GregDM | C27: XPSDG_GregDM | D27: Actions Européennes | E27: Gérant | G27: Gérant - Actions européennes | H27: 2004 | I27: =YEAR(TODAY())-H27 -> 22 | J27: 2024 | K27: =YEAR(TODAY())-J27 -> 2
A28: Guillaume Mouton | B28: XPINDUS_Mouton | C28: XPSDG_Mouton | D28: Négociation | E28: Négociateur | G28: Négociateur | H28: 2020 | I28: =YEAR(TODAY())-H28 -> 6 | J28: 2020 | K28: =YEAR(TODAY())-J28 -> 6
A29: Henri Captier | B29: XPINDUS_Captier | C29: XPSDG_Captier | D29: Valor (gamme) | E29: Gérant | G29: Gérant de portefeuilles diversifiés et actions internationales | H29: 2018 | I29: =YEAR(TODAY())-H29 -> 8 | J29: 2018 | K29: =YEAR(TODAY())-J29 -> 8
A30: Henry Ndong | B30: XPINDUS_Ndong | C30: XPSDG_Ndong | D30: Obligataire | E30: Analyste | F30: Analyste | G30: Responsable de l'analyse crédit | H30: 2010 | I30: =YEAR(TODAY())-H30 -> 16 | J30: 2016 | K30: =YEAR(TODAY())-J30 -> 10
A31: Inas Rachidi | B31: XPINDUS_IRachidi | C31: XPSDG_IRachidi | D31: Multigestion (Architecture ouverte) | E31: Analyste | F31: Assistant de gestion | G31: Assistant de gestion multigestion | H31: 2021 | I31: =YEAR(TODAY())-H31 -> 5 | J31: 2022 | K31: =YEAR(TODAY())-J31 -> 4
A32: Iris Bastien | B32: XPINDUS_IrisBas | C32: XPSDG_IrisBas | D32: Multigestion (Architecture ouverte) | E32: Analyste | F32: Analyste | G32: Analyste multigestion | H32: 2020 | I32: =YEAR(TODAY())-H32 -> 6 | J32: 2025 | K32: =YEAR(TODAY())-J32 -> 1
A33: Jade Weill | B33: XPINDUS_JWeill | C33: XPSDG_JWeill | D33: Multigestion (Architecture ouverte) | E33: Analyste | F33: Analyste | G33: Analyste multigestion | H33: 2011 | I33: =YEAR(TODAY())-H33 -> 15 | J33: 2011 | K33: =YEAR(TODAY())-J33 -> 15
A34: Jennifer Ruau | B34: XPINDUS_JRuau | C34: XPSDG_JRuau | D34: Multigestion (Architecture ouverte) | E34: Analyste | F34: Analyste | G34: Analyste multigestion | H34: 2021 | I34: =YEAR(TODAY())-H34 -> 5 | J34: 2025 | K34: =YEAR(TODAY())-J34 -> 1
A35: Jérôme Loire | B35: XPINDUS_JLoire | C35: XPSDG_JLoire | D35: Obligataire | E35: Analyste | F35: Analyste | G35: Analyste crédit | H35: 1993 | I35: =YEAR(TODAY())-H35 -> 33 | J35: 2012 | K35: =YEAR(TODAY())-J35 -> 14
A36: Julien Baumont | B36: XPINDUS_JBaumont | C36: XPSDG_Jbaumont | D36: Négociation | E36: Négociateur | G36: Négociateur | H36: 2010 | I36: =YEAR(TODAY())-H36 -> 16 | J36: 2014 | K36: =YEAR(TODAY())-J36 -> 12
A37: Julien Boy | B37: XPINDUS_JBoy | C37: XPSDG_JBoy | D37: Obligataire | E37: Gérant | G37: Gérant obligataire - Spécialisation : Emprunts d'Etats et Inflation | H37: 2006 | I37: =YEAR(TODAY())-H37 -> 20 | J37: 2006 | K37: =YEAR(TODAY())-J37 -> 20
A38: Julien Dapsens | B38: XPINDUS_JDapsens | C38: XPSDG_JDapsens | D38: Multigestion (Architecture ouverte) | E38: Gérant | G38: Gérant en Architecture Ouverte | H38: 2014 | I38: =YEAR(TODAY())-H38 -> 12 | J38: 2026 | K38: =YEAR(TODAY())-J38 -> 0
A39: Klara Sok | B39: XPINDUS_Sok | C39: XPSDG_Sok | D39: Valor (gamme) | E39: Gérant | G39: Co-gérante du portefeuille R-co Thematic Blockchain Global Equity | H39: 2007 | I39: =(YEAR(TODAY())-H39)-4 -> 15 | J39: 2022 | K39: =YEAR(TODAY())-J39 -> 4
A40: Kristell Agaësse | B40: XPINDUS_KriAgaesse | C40: XPSDG_KriAgaesse | D40: Obligataire | E40: Gérant | G40: Responsable de la Gestion High Yield & Obligations Convertibles | H40: 2000 | I40: =YEAR(TODAY())-H40 -> 26 | J40: 2006 | K40: =YEAR(TODAY())-J40 -> 20
A41: Laurent Cheng | B41: XPINDUS_LCheng | C41: XPSDG_LCheng | D41: Multigestion (Architecture ouverte) | E41: Analyste | F41: Assistant de gestion | G41: Assistant de gestion multigestion | H41: 2001 | I41: =YEAR(TODAY())-H41 -> 25 | J41: 2009 | K41: =YEAR(TODAY())-J41 -> 17
A42: Linh Mansion | B42: XPINDUS_LMansion | C42: XPSDG_LMansion | D42: Multigestion (Architecture ouverte) | E42: Analyste | F42: Analyste | G42: Responsable de la Recherche - Architecture ouverte | H42: 2000 | I42: =YEAR(TODAY())-H42 -> 26 | J42: 2007 | K42: =YEAR(TODAY())-J42 -> 19
A43: Louise Li | B43: XPINDUS_Li | C43: XPSDG_Li | D43: Valor (gamme) | E43: Analyste | F43: Analyste | G43: Analyste – actions internationales | H43: 2020 | I43: =YEAR(TODAY())-H43 -> 6 | J43: 2020 | K43: =YEAR(TODAY())-J43 -> 6
A44: Lucas Fallone | B44: XPINDUS_LFallone | C44: XPSDG_LFallone | D44: Actions Européennes | E44: Analyste | F44: Analyste/ Assistant de gestion | G44: Analyste / Assistant de gestion | H44: 2019 | I44: =YEAR(TODAY())-H44 -> 7 | J44: 2022 | K44: =YEAR(TODAY())-J44 -> 4
A45: Ludivine de Quincerot | B45: XPINDUS_LDQ | C45: XPSDG_LDQ | D45: Investissement Durable | E45: Comité exécutif | F45: Gérant | G45: Managing Director, Responsable de l'investissement durable Gérante de fonds diversifiés | H45: 1998 | I45: =YEAR(TODAY())-H45 -> 28 | J45: 2004 | K45: =YEAR(TODAY())-J45 -> 22
A46: Marc Terras | B46: XPINDUS_MTerras | C46: XPSDG_MTerras | D46: Multigestion (Architecture ouverte) | E46: Gérant | G46: Directeur de la gestion en architecture ouverte | H46: 1996 | I46: =YEAR(TODAY())-H46 -> 30 | J46: 2000 | K46: =YEAR(TODAY())-J46 -> 26
A47: Marc-Antoine Collard | B47: XPINDUS_MAC | C47: XPSDG_MAC | D47: Recherche macroéconomique | E47: Analyste | F47: Analyste | G47: Chef économiste – Directeur de la recherche macroéconomique | H47: 2004 | I47: =YEAR(TODAY())-H47 -> 22 | J47: 2014 | K47: =YEAR(TODAY())-J47 -> 12
A48: Mathieu Six | B48: XPINDUS_MSix | C48: XPSDG_MSix | D48: Multigestion (Architecture ouverte) | E48: Gérant | G48: Gérant en Architecture Ouverte | H48: 2006 | I48: =YEAR(TODAY())-H48 -> 20 | J48: 2011 | K48: =YEAR(TODAY())-J48 -> 15
A49: Michael Longeard | B49: XPINDUS_MichaLon | C49: XPSDG_MichaLon | D49: Obligataire | E49: Gérant | G49: Gérant High Yield / Convertibles | H49: 2007 | I49: =YEAR(TODAY())-H49 -> 19 | J49: 2023 | K49: =YEAR(TODAY())-J49 -> 3
A50: Mirthula Pirapakaran | B50: XPINDUS_MirthulaPi | C50: XPSDG_MirthulaPi | D50: Obligataire | E50: Analyste | F50: Analyste | G50: Analyste crédit | H50: 2018 | I50: =YEAR(TODAY())-H50 -> 8 | J50: 2021 | K50: =YEAR(TODAY())-J50 -> 5
A51: Morgane Wespieser | B51: XPINDUS_MorganeWes | C51: XPSDG_MorganeWes | D51: Multigestion (Architecture ouverte) | E51: Analyste | F51: Product Specialist | G51: Analyste multigestion | H51: 2019 | I51: =YEAR(TODAY())-H51 -> 7 | J51: 2019 | K51: =YEAR(TODAY())-J51 -> 7
A52: Natacha Rousset | B52: XPINDUS_Rousset | C52: XPSDG_Rousset | D52: Actions Européennes | E52: Analyste | F52: Analyste | G52: Analyste Actions Européennes | H52: 1998 | I52: =YEAR(TODAY())-H52 -> 28 | J52: 2004 | K52: =YEAR(TODAY())-J52 -> 22
A53: Natally Loaiza Santamaria | B53: XPINDUS_NLS | C53: XPSDG_NLS | D53: Obligataire | E53: Analyste | F53: Analyste | G53: Analyste crédit ESG | H53: 2018 | I53: =YEAR(TODAY())-H53 -> 8 | J53: 2023 | K53: =YEAR(TODAY())-J53 -> 3
A54: Nathalie Bourdoncle | B54: XPINDUS_Bourdoncle | C54: XPSDG_Bourdoncle | D54: Actions Thématiques | E54: Gérant | G54: Gérante - Actions thématiques | H54: 1992 | I54: =YEAR(TODAY())-H54 -> 34 | J54: 2007 | K54: =YEAR(TODAY())-J54 -> 19
A55: Nathan Gamon | B55: XPINDUS_Gamon | C55: XPSDG_Gamon | D55: Obligataire | E55: Analyste | F55: Assistant de gestion | G55: Equipe Gestion Obligataire | H55: 2026 | I55: =YEAR(TODAY())-H55 -> 0 | J55: 2026 | K55: =YEAR(TODAY())-J55 -> 0
A56: Nicolas Pelinq | B56: XPINDUS_Pelinq | C56: XPSDG_Pelinq | D56: Négociation | E56: Négociateur | G56: Négociateur | H56: 1997 | I56: =YEAR(TODAY())-H56 -> 29 | J56: 2018 | K56: =YEAR(TODAY())-J56 -> 8
A57: Nicolas Racaud | B57: XPINDUS_NicRacaud | C57: XPSDG_NicRacaud | D57: Obligataire | E57: Gérant | G57: Gérant obligataire et référent ESG - Spécialisation : Crédit IG, Crossover, et fonds ESG | H57: 1999 | I57: =YEAR(TODAY())-H57 -> 27 | J57: 1999 | K57: =YEAR(TODAY())-J57 -> 27
A58: Nicolas Weber | B58: XPINDUS_NicWeber | C58: XPSDG_NicWeber | D58: Négociation | E58: Négociateur | G58: Négociateur | H58: 2012 | I58: =YEAR(TODAY())-H58 -> 14 | J58: 2025 | K58: =YEAR(TODAY())-J58 -> 1
A59: Nursultan Yessirkep | B59: XPINDUS_NursYessirkep | C59: XPSDG_NursYessirkep | D59: Risques | E59: Analyste Risques | G59: Analyste Risques | H59: 2015 | I59: =YEAR(TODAY())-H59 -> 11 | J59: 2025 | K59: =YEAR(TODAY())-J59 -> 1
A60: Paul Contamin | B60: XPINDUS_PContamin | C60: XPSDG_PContamin | D60: Valor (gamme) | E60: Analyste | F60: Analyste | G60: Analyste – actions internationales | H60: 2026 | I60: =YEAR(TODAY())-H60 -> 0 | J60: 2026 | K60: =YEAR(TODAY())-J60 -> 0
A61: Paul Reuge | B61: XPINDUS_PReuge | C61: XPSDG_PReuge | D61: Actions Thématiques | E61: Gérant | G61: Gérant - Actions européennes | H61: 2007 | I61: =YEAR(TODAY())-H61 -> 19 | J61: 2014 | K61: =YEAR(TODAY())-J61 -> 12
A62: Philippe Lomné | B62: XPINDUS_PLomné | C62: XPSDG_PLomné | D62: Obligataire | E62: Gérant | G62: Gérant obligataire - Spécialisation : Crédit IG et Crossover | H62: 2010 | I62: =YEAR(TODAY())-H62 -> 16 | J62: 2010 | K62: =YEAR(TODAY())-J62 -> 16
A63: Pierre Baudard | B63: XPINDUS_PB | C63: XPSDG_PB | D63: Comité exécutif | E63: Comité exécutif | G63: Associé-Gérant, Directeur Général | H63: 1999 | I63: =YEAR(TODAY())-H63 -> 27 | J63: 2015 | K63: =YEAR(TODAY())-J63 -> 11
A64: Pierre Hauvette | B64: XPINDUS_Phauvette | C64: XPSDG_Phauvette | D64: Multigestion (Architecture ouverte) | E64: Analyste | F64: Analyste | G64: Analyste multigestion | H64: 2006 | I64: =YEAR(TODAY())-H64 -> 20 | J64: 2011 | K64: =YEAR(TODAY())-J64 -> 15
A65: Salma Alami-Drideb | B65: XPINDUS_SalmaAD | C65: XPSDG_SalmaAD | D65: Risques | E65: Analyste Risques | G65: Analyste Risques | H65: 2011 | I65: =YEAR(TODAY())-H65 -> 15 | J65: 2011 | K65: =YEAR(TODAY())-J65 -> 15
A66: Samuel Gruen | B66: XPINDUS_SGruen | C66: XPSDG_SGruen | D66: Obligataire | E66: Gérant | G66: Gérant obligataire _ Spécialisation : Crédit IG, Crossover | H66: 2011 | I66: =YEAR(TODAY())-H66 -> 15 | J66: 2023 | K66: =YEAR(TODAY())-J66 -> 3
A67: Sergio Gallo | B67: XPINDUS_SGallo | C67: XPSDG_SGallo | D67: Valor (gamme) | E67: Analyste | F67: Analyste | G67: Analyste – actions internationales | H67: 2021 | I67: =YEAR(TODAY())-H67 -> 5 | J67: 2023 | K67: =YEAR(TODAY())-J67 -> 3
A68: Solweig Pierronnet | B68: XPINDUS_SolweigP | C68: XPSDG_SolweigP | D68: Obligataire | E68: Analyste | F68: Analyste | G68: Analyste crédit | H68: 2012 | I68: =YEAR(TODAY())-H68 -> 14 | J68: 2023 | K68: =YEAR(TODAY())-J68 -> 3
A69: Tatiana Velandia | B69: XPINDUS_TVelandia | C69: XPSDG_TVelandia | D69: Actions Européennes | E69: Analyste | F69: Analyste | G69: Analyste Actions Européennes | H69: 2019 | I69: =YEAR(TODAY())-H69 -> 7 | J69: 2024 | K69: =YEAR(TODAY())-J69 -> 2
A70: Théo Baptiste | B70: XPINDUS_TBaptiste | C70: XPSDG_TBaptiste | D70: Investissement Durable | E70: Analyste | F70: Analyste | G70: Data Scientist ESG & Ingénieur financier | H70: 2025 | I70: =YEAR(TODAY())-H70 -> 1 | J70: 2025 | K70: =YEAR(TODAY())-J70 -> 1
A71: Thierry Combes | B71: XPINDUS_TCombes | C71: XPSDG_TCombes | D71: Actions USA | E71: Gérant | G71: Gérant - Actions américaines | H71: 2001 | I71: =YEAR(TODAY())-H71 -> 25 | J71: 2006 | K71: =YEAR(TODAY())-J71 -> 20
A72: Thierry Rigaudière | B72: XPINDUS_TRigaud | C72: XPSDG_TRigaud | D72: Actions Thématiques | E72: Gérant | G72: Responsable de la gestion thématique | H72: 1989 | I72: =YEAR(TODAY())-H72 -> 37 | J72: 2012 | K72: =YEAR(TODAY())-J72 -> 14
A73: Thomas Ayache | B73: XPINDUS_TAyache | C73: XPSDG_TAyache | D73: Multigestion (Architecture ouverte) | E73: Gérant | G73: Gérant en Architecture Ouverte | H73: 1999 | I73: =YEAR(TODAY())-H73 -> 27 | J73: 2005 | K73: =YEAR(TODAY())-J73 -> 21
A74: Thomas Vincent | B74: XPINDUS_TVincent | C74: XPSDG_TVincent | D74: Investissement Durable | E74: Analyste | F74: Analyste | G74: Data Scientist ESG & Ingénieur financier | H74: 2005 | I74: =YEAR(TODAY())-H74 -> 21 | J74: 2005 | K74: =YEAR(TODAY())-J74 -> 21
A75: Ugo Kiraz | B75: XPINDUS_UKiraz | C75: XPSDG_UKiraz | D75: Valor (gamme) | E75: Analyste | F75: Analyste | G75: Analyste – actions internationales | H75: 2022 | I75: =YEAR(TODAY())-H75 -> 4 | J75: 2023 | K75: =YEAR(TODAY())-J75 -> 3
A76: Valérie Oelhoffen | B76: XPINDUS_ValOel | C76: XPSDG_ValOel | D76: Actions Thématiques | E76: Gérant | G76: Gérante - Actions thématiques | H76: 1991 | I76: =YEAR(TODAY())-H76 -> 35 | J76: 2010 | K76: =YEAR(TODAY())-J76 -> 16
A77: Vincent Gouzon | B77: XPINDUS_VGouzon | C77: XPSDG_VGouzon | D77: Solutions d'investissement | E77: Analyste | F77: Analyste | G77: Responsable Solutions d'Investissement | H77: 2005 | I77: =YEAR(TODAY())-H77 -> 21 | J77: 2006 | K77: =YEAR(TODAY())-J77 -> 20
A78: Vincent Imeneuraët | B78: XPINDUS_VImeneuraet | C78: XPSDG_VImeneuraet | D78: Actions Européennes | E78: Gérant | G78: Gérant - Actions européennes et Responsable de l'analyse actions européennes | H78: 2000 | I78: =YEAR(TODAY())-H78 -> 26 | J78: 2013 | K78: =YEAR(TODAY())-J78 -> 13
A79: Vincent Rasclard | B79: XPINDUS_VR | C79: XPSDG_VR | D79: Marketing | E79: Comité exécutif | G79: Responsable Marketing, Reporting et Service Client | H79: 1998 | I79: =YEAR(TODAY())-H79 -> 28 | J79: 2000 | K79: =YEAR(TODAY())-J79 -> 26
A80: Yann Roux | B80: XPINDUS_YRoux | C80: XPSDG_YRoux | D80: Obligataire | E80: Gérant | G80: Gérant obligataire - Spécialisation : Monétaire et Court terme | H80: 2008 | I80: =YEAR(TODAY())-H80 -> 18 | J80: 2010 | K80: =YEAR(TODAY())-J80 -> 16
A81: Yoann Ignatiew | B81: XPINDUS_YI | C81: XPSDG_YI | D81: Valor (gamme) | E81: Comité exécutif | F81: Gérant | G81: Associé-Gérant, Responsable Gestion Internationale et gestion diversifiée | H81: 1990 | I81: =YEAR(TODAY())-H81 -> 36 | J81: 2008 | K81: =YEAR(TODAY())-J81 -> 18
B85: Expérience moyenne de l'équipe
B86: Obligataire (total) | C86: XPMOYAllTeamTaux
B87: Obligataire (gérant + assistant) | C87: XPMOYPMTaux
B88: Obligataire (analyste) | C88: XPMOYAnalystesTaux
B90: Actions européennes (total) | C90: XPMOYAllEUEquities
B91: Actions thématiques (total) | C91: XPMOYAllThematics
B92: Actions européennes (gérants) | C92: XPMOYPMEU Equities
B93: Actions européennes (analystes) | C93: XPMOYAnalystesActions
B95: Valor (total) | C95: XPMOYAllValorTeam
B96: Gérants Valor | C96: XPMOYPMValorTeam
B97: Analystes Valor | C97: XPMOYAnalystesValor
B99: Multigestion (total) | C99: XPMOYMulti
B100: Multigestion (gérants) | C100: XPMOYPMMulti
B101: Multigestion analystes | C101: XPMOYAnalystesMulti
B103: Membres de l'équipe
B104: Obligataire (analystes) | C104: NAMETEAMTaux
B105: Actions européennes (analystes) | C105: NAMETEAMEUEquities
B106: Analystes Valor | C106: NAMETEAMValor
B107: Multigestion analystes | C107: NAMETEAMMulti
...

Sheet Tab_Suivi 
A1: SUIVI QVIDIAN — MERGE CODES EXPÉRIENCE
A2: Pilotage fonds par fonds | Campagne 2026 | Préparation des activations 2027
A3: PÉRIMÈTRE | C3: FONDS TERMINÉS | E3: ÉTAPES VALIDÉES | G3: EN COURS | I3: CAS 2027
A4: =COUNTA(A9:A41) -> 33 | C4: =COUNTIF(D9:D41,"Terminé") -> 0 | E4: =(COUNTIF(B9:B41,TRUE)+COUNTIF(C9:C41,TRUE))/(COUNTA(A9:A41)*2) -> 0 | G4: =COUNTIF(D9:D41,"En cours") -> 0 | I4: =COUNTIF(H9:H41,"<>") -> 0
A6: MODE D’EMPLOI • Cochez Industrie et Société lorsque les merge codes sont intégrés. Pour une personne à 0 an, laissez le code hors du texte et renseignez l’ID concerné ainsi que son nom dans les colonnes dédiées à 2027.
A8: Fonds | B8: Industrie OK | C8: Société OK | D8: Statut | E8: ID + merge code Industrie | F8: ID + merge code Société | G8: ID sans code (0 an) | H8: Personne à activer en 2027 | I8: Notes / blocages | J8: Dernière MAJ
A9: R-co Conviction Credit 12M Euro | B9: FALSE | C9: FALSE | D9: =IF(AND(B9,C9),"Terminé",IF(OR(B9,C9),"En cours","À faire")) -> À faire
A10: R-co Conviction Credit Euro | B10: FALSE | C10: FALSE | D10: =IF(AND(B10,C10),"Terminé",IF(OR(B10,C10),"En cours","À faire")) -> À faire
A11: R-co Conviction Credit SD Euro | B11: FALSE | C11: FALSE | D11: =IF(AND(B11,C11),"Terminé",IF(OR(B11,C11),"En cours","À faire")) -> À faire
A12: R-co Conviction High Yield Euro | B12: FALSE | C12: FALSE | D12: =IF(AND(B12,C12),"Terminé",IF(OR(B12,C12),"En cours","À faire")) -> À faire
A13: R-co Conviction High Yield SD Euro | B13: FALSE | C13: FALSE | D13: =IF(AND(B13,C13),"Terminé",IF(OR(B13,C13),"En cours","À faire")) -> À faire
A14: R-co Conviction Subfin | B14: FALSE | C14: FALSE | D14: =IF(AND(B14,C14),"Terminé",IF(OR(B14,C14),"En cours","À faire")) -> À faire
A15: R-co Sérénité PEA | B15: FALSE | C15: FALSE | D15: =IF(AND(B15,C15),"Terminé",IF(OR(B15,C15),"En cours","À faire")) -> À faire
A16: R-co Target 2026 HY | B16: FALSE | C16: FALSE | D16: =IF(AND(B16,C16),"Terminé",IF(OR(B16,C16),"En cours","À faire")) -> À faire
A17: R-co Target 2027 HY | B17: FALSE | C17: FALSE | D17: =IF(AND(B17,C17),"Terminé",IF(OR(B17,C17),"En cours","À faire")) -> À faire
A18: R-co Target 2028 IG | B18: FALSE | C18: FALSE | D18: =IF(AND(B18,C18),"Terminé",IF(OR(B18,C18),"En cours","À faire")) -> À faire
A19: R-co Target 2029 HY | B19: FALSE | C19: FALSE | D19: =IF(AND(B19,C19),"Terminé",IF(OR(B19,C19),"En cours","À faire")) -> À faire
A20: R-co Target 2029 IG | B20: FALSE | C20: FALSE | D20: =IF(AND(B20,C20),"Terminé",IF(OR(B20,C20),"En cours","À faire")) -> À faire
... A41: RMM Court Terme | B41: FALSE | C41: FALSE | D41: =IF(AND(B41,C41),"Terminé",IF(OR(B41,C41),"En cours","À faire")) -> À faire
A44: À PRÉPARER POUR 2027 — COLLABORATEURS À 0 AN
A45: Les codes ci-dessous ne doivent pas être intégrés en 2026. Ils deviennent les points de contrôle prioritaires lors du prochain changement d’année.
A47: Collaborateur | B47: Exp. industrie | C47: Exp. société | D47: Code industrie si 0 | E47: Code société si 0
A48: {=_xlfn._xlws.FILTER(CHOOSE({1,2,3,4,5},Data!A2:A81,Data!I2:I81,Data!K2:K81,IF(Data!I2:I81=0,Data!B2:B81,""),IF(Data!K2:K81=0,Data!C2:C81,"")),(Data!I2:I81=0)+(Data!K2:K81=0),"Aucun collaborateur à 0 an")} -> Augustin Giros | B48: 2026 | C48: 0 | E48: XPSDG_AGiros
A49: Julien Dapsens | B49: 12 | C49: 0 | E49: XPSDG_JDapsens
A50: Nathan Gamon | B50: 0 | C50: 0 | D50: XPINDUS_Gamon | E50: XPSDG_Gamon
A51: Paul Contamin | B51: 0 | C51: 0 | D51: XPINDUS_PContamin | E51: XPSDG_PContamin

Sheet Exp moyenne par équipe gestion
B2: Expérience moyenne par équipe
B4: Equipe | C4: Industrie | D4: Société | E4: Nombre de personnes dans l'équipe | F4: Membre de l'équipe?
B5: Equipe obligataire (total) | C5: =AVERAGE(Data!#REF!,Data!I13,Data!I15,Data!I16,Data!I18,Data!I19,Data!I20,Data!I21,Data!I22,Data!I23,Data!I24,Data!I25,Data!I26,Data!I27) -> #REF! | D5: =AVERAGE(Data!#REF!,Data!K13,Data!K15,Data!K16,Data!K18,Data!K19,Data!K20,Data!K21,Data!K22,Data!K23,Data!K24,Data!K25,Data!K26,Data!K27) -> #REF! | E5: =SUM(E6:E7) -> 14
B6: Gérants | C6: =AVERAGE(Data!#REF!,Data!I13,Data!I15,Data!I16,Data!I18,Data!I19,Data!I20,Data!I21,Data!I22) -> #REF! | D6: =AVERAGE(Data!#REF!,Data!K13,Data!K15,Data!K16,Data!K18,Data!K19,Data!K20,Data!K21,Data!K22) -> #REF! | E6: 9 | F6: Emmanuel Petit, Julien Boy, Nicolas Racaud, Philippe Lomné, Kristell Agaësse, Michael Longeard, Yann Roux, Samuel Gruen, Antoine Da Silva | G6: assistant de gestion
B7: Analystes crédit | C7: =AVERAGE(Data!I23,Data!I24,Data!I25,Data!I26,Data!I27) -> 23.8 | D7: =AVERAGE(Data!K23,Data!K24,Data!K25,Data!K26,Data!K27) -> 9.6 | E7: 5 | F7: Henry Ndong, Jérôme Loire, Mirthula Pirapakaran, Solweig Pierronnet, Natally Loaiza Santamaria
B8: Equipe multigestion (total) | C8: =AVERAGE(Data!I62,Data!I63,Data!I64,Data!I65,Data!I66,Data!I67,Data!I68,Data!#REF!,Data!#REF!,Data!I69) -> #REF! | D8: =AVERAGE(Data!K62,Data!K63,Data!K64,Data!K65,Data!K66,Data!K67,Data!K68,Data!#REF!,Data!#REF!,Data!K69) -> #REF! | E8: =SUM(E9:E10) -> 10
B9: Gérants | C9: =AVERAGE(Data!I62,Data!I63,Data!I64,Data!I65,Data!I69) -> 17 | D9: =AVERAGE(Data!K62,Data!K63,Data!K64,Data!K65,Data!I69) -> 12.8 | E9: 5 | F9: Marc Terras, Thomas Ayache, Stéphane Gaultier de Kermoal, Mathieu Six, Laurent Cheng | G9: assistant de gestion
B10: Analystes multigestion | C10: =AVERAGE(Data!I66,Data!I67,Data!I68,Data!#REF!,Data!#REF!) -> #REF! | D10: =AVERAGE(Data!K66,Data!K67,Data!K68,Data!#REF!,Data!#REF!) -> #REF! | E10: 5 | F10: Pierre Hauvette, Linh Mansion, Jade Weill, Morgane Wespieser, Ambre Laurenson,
B11: Gamme Valor (total)* | C11: =AVERAGE(Data!I54,Data!I56,Data!I57,Data!I58,Data!I59,Data!I60,Data!#REF!,Data!I61) -> #REF! | D11: =AVERAGE(Data!K54,Data!K56,Data!K57,Data!K58,Data!K59,Data!K60,Data!#REF!,Data!K61) -> #REF! | E11: =SUM(E12:E14) -> 8 | G11: *hors Valor Balanced
B12: Gérants | C12: =AVERAGE(Data!I54,Data!I56,Data!I57) -> 30 | D12: =AVERAGE(Data!K54,Data!K56,Data!K57) -> 18 | E12: 3 | F12: Yoann Ignatiew, Charles-Edouard Bilbault, Klara Sok
B13: Analystes dédiés | C13: =AVERAGE(Data!I58,Data!I59,Data!I60,Data!#REF!) -> #REF! | D13: =AVERAGE(Data!K58,Data!K59,Data!K60,Data!#REF!) -> #REF! | E13: 4 | F13: Henri Captier, Louise Zhuoya Li, Sergio Gallo, Abel Amine
B14: Product specialist | C14: =AVERAGE(Data!I61) -> 19 | D14: =AVERAGE(Data!K61) -> 12 | E14: 1 | F14: Elsa Fernandez
B15: Actions Zones Européennes | E15: =SUM(E16:E17)+E19 -> 11 | G15: + gestion thématique
B16: Gérants | C16: =AVERAGE(Data!#REF!,Data!I28,Data!I30) -> #REF! | D16: =AVERAGE(Data!#REF!,Data!K28,Data!K30) -> #REF! | E16: 3 | F16: Anthony Bailly, Vincent Imeneuraët, Ugo Kiraz | G16: assistant de gestion
B17: Analystes | C17: =AVERAGE(Data!I45,Data!I46,Data!#REF!) -> #REF! | D17: =AVERAGE(Data!#REF!,Data!K46,Data!K45) -> #REF! | E17: 3 | F17: Gabriel Hors, Natacha Rousset, Jorge Velandia
B18: Thématiques et Small Cap (total)
B19: Gérants | C19: =AVERAGE(Data!I41,Data!I42,Data!#REF!,Data!I32,Data!#REF!) -> #REF! | D19: =AVERAGE(Data!K32,Data!#REF!,Data!K41,Data!K42,Data!#REF!) -> #REF! | E19: 5 | F19: Valérie Oelhoffen, Nathalie Bourdoncle, Thierry Rigaudière, Paul Reuge, Alban Seydoux
B20: Equipe Investissement Durable (total) | C20: =AVERAGE(Data!I49,Data!I50,Data!I51,Data!I52,Data!I53) -> 14 | D20: =AVERAGE(Data!K49,Data!K50,Data!K51,Data!K52,Data!K53) -> 8 | E20: =(SUM(E21:E23)+1) -> 5 | F20: +Ludivine de Quincerot | G20: dans la formule il y a un +1 pour LQ
B21: Spécialistes ESG | C21: =AVERAGE(Data!I50,Data!I51) -> 7.5 | D21: =AVERAGE(Data!K50,Data!K51) -> 6 | E21: 2 | F21: Andrea Sekularac, Alice Lagny
B22: Analyste ESG et responsable de l'engagement | C22: =AVERAGE(Data!I52) -> 28 | D22: =AVERAGE(Data!K52) -> 22 | E22: 1 | F22: Edward Luu
B23: Ingénieur financier et ESG data scientist | C23: =AVERAGE(Data!I53) -> 8 | D23: =AVERAGE(Data!K53) -> 3 | E23: 1 | F23: Thomas Vincent
B24: Equipe Solutions d'Investissement (total) | C24: =AVERAGE(Data!I70,Data!#REF!) -> #REF! | D24: =AVERAGE(Data!K70,Data!#REF!) -> #REF! | E24: 2 | F24: Etienne Rouzeau, Vincent Gouzon
B25: Analystes Private Assets (total) | C25: =AVERAGE(Data!#REF!,Data!I71,Data!I72) -> #REF! | D25: =AVERAGE(Data!#REF!,Data!K71,Data!K72) -> #REF! | E25: 3 | F25: Jean-Guillaume Demares, Gilles Pophillat, Louis Perfumo | G25: ne font plus partie AM => Banque Privée RMM
B26: Equipe Négociateurs (total) | C26: =AVERAGE(Data!I74,Data!I76,Data!#REF!) -> #REF! | D26: =AVERAGE(Data!K74,Data!K76,Data!#REF!) -> #REF! | E26: 3 | F26: Nicolas Antérieux, Julien Baumont, Thierry Merceron
